modelingtools/__init__.py
modelingtools/evaluationtools.py
modelingtools/testingtools.py
modelingtools/trainingtools.py
tests/__init__.py
tests/test_evaluationtools.py
tests/test_trainingtools.py
modelingtools-0.3.1.dist-info/LICENSE
modelingtools-0.3.1.dist-info/METADATA
modelingtools-0.3.1.dist-info/WHEEL
modelingtools-0.3.1.dist-info/top_level.txt
modelingtools-0.3.1.dist-info/RECORD
