Metadata-Version: 2.1
Name: modelingtools
Version: 0.3.1
Summary: Tools to make modeling easier - Work in progress
Home-page: https://github.com/jeremymiller00/modelingtools
Author: Jeremy Miller
Author-email: jeremymiller00@gmail.com
Project-URL: Bug Tracker, https://github.com/jeremymiller00/modelingtools/issues
Classifier: Programming Language :: Python :: 3
Classifier: Programming Language :: Python :: 3.7
Classifier: Programming Language :: Python :: 3.8
Classifier: Programming Language :: Python :: 3.9
Classifier: Programming Language :: Python :: 3.10
Classifier: License :: OSI Approved :: MIT License
Classifier: Operating System :: OS Independent
Requires-Python: >=3.7
License-File: LICENSE
Requires-Dist: scikit-learn
Requires-Dist: numpy
Requires-Dist: matplotlib
Requires-Dist: statsmodels
Requires-Dist: pandas
